LICENSE
MANIFEST.in
README.rst
ipaddress.py
setup.cfg
setup.py
test_ipaddress.py
backport_ipaddress.egg-info/PKG-INFO
backport_ipaddress.egg-info/SOURCES.txt
backport_ipaddress.egg-info/dependency_links.txt
backport_ipaddress.egg-info/top_level.txt
backport_ipaddress.egg-info/zip-safe