Metadata-Version: 1.1
Name: backport-ipaddress
Version: 0.1
Summary: Backport of Python 3's ipaddress module
Home-page: http://github.com/sk-/backport_ipaddress
Author: Sebastian Kreft
Author-email: UNKNOWN
License: UNKNOWN
Platform: UNKNOWN
Classifier: Development Status :: 5 - Production/Stable
Classifier: Intended Audience :: Developers
Classifier: License :: OSI Approved :: Python Software Foundation License
Classifier: Programming Language :: Python :: 2.6
Classifier: Programming Language :: Python :: 2.7
